Metadata-Version: 2.1
Name: oncalendar
Version: 1.0
Summary: Systemd OnCalendar expression parser and evaluator
Home-page: https://github.com/cuu508/oncalendar
Author: Pēteris Caune
Author-email: cuu508@monkeyseemonkeydo.lv
License: BSD
Project-URL: Changelog, https://github.com/cuu508/oncalendar/blob/main/CHANGELOG.md
Keywords: systemd,oncalendar,calendar,schedule
Platform: any
Classifier: Development Status :: 3 - Alpha
Classifier: Intended Audience :: Developers
Classifier: License :: OSI Approved :: BSD License
Classifier: Operating System :: OS Independent
Classifier: Programming Language :: Python
Classifier: Programming Language :: Python :: 3
Classifier: Topic :: Software Development :: Libraries :: Python Modules
Requires-Python: >= 3.10
License-File: LICENSE
